{
  "@context": [
    "https://www.w3.org/2018/credentials/v1",
    "https://w3id.org/security/suites/jws-2020/v1",
    {
      "@vocab": "https://example.com/#"
    }
  ],
  "type": [
    "VerifiableCredential"
  ],
  "issuer": "did:example:123",
  "issuanceDate": "2021-01-01T19:23:24Z",
  "expirationDate": "2031-01-01T19:23:24Z",
  "credentialSubject": {
    "id": "did:example:456",
    "type": "Person"
  },
  "proof": {
    "type": "JsonWebSignature2020",
    "created": "2021-11-19T00:41:17Z",
    "verificationMethod": "did:example:123#key-0",
    "proofPurpose": "assertionMethod",
    "jws": "eyJhbGciOiJFZERTQSIsImI2NCI6ZmFsc2UsImNyaXQiOlsiYjY0Il19..5Uz4vqnVrHOf3m_6iFHAJLlW8cZl0guk0Yu5vHhD4Dv47TuNQqDldl9D3Xz-TfirLgmXZ3n5PTsZD--0VyI2DQ"
  }
}