{
  "@context": [
    "https://www.w3.org/2018/credentials/v1",
    "https://w3id.org/security/suites/jws-2020/v1"
  ],
  "type": [
    "VerifiablePresentation"
  ],
  "holder": "did:example:123",
  "proof": {
    "type": "JsonWebSignature2020",
    "created": "2022-03-09T00:20:46Z",
    "verificationMethod": "did:example:123#key-1",
    "proofPurpose": "authentication",
    "challenge": "123",
    "jws": "eyJhbGciOiJFUzI1NksiLCJiNjQiOmZhbHNlLCJjcml0IjpbImI2NCJdfQ..g-0cfn7_EKan5ICaUtgDlFH-KEHYJCO8L9YtfUDHvw0FzFNnUnT-UArZyU0c3Oo1jSzwik-HPdVjfrIADoesrQ"
  }
}