{
  "@context": [
    "https://www.w3.org/2018/credentials/v1",
    "https://w3id.org/security/suites/jws-2020/v1"
  ],
  "id": "urn:uuid:789",
  "type": [
    "VerifiablePresentation"
  ],
  "holder": "did:example:123",
  "verifiableCredential": [],
  "proof": {
    "type": "JsonWebSignature2020",
    "created": "2021-09-28T22:14:35Z",
    "verificationMethod": "did:example:123#key-0",
    "proofPurpose": "authentication",
    "challenge": "123",
    "jws": "eyJhbGciOiJFZERTQSIsImI2NCI6ZmFsc2UsImNyaXQiOlsiYjY0Il19..whZqdzRkQoGPthcGyfvETdHYVNGx2uhLk79qnU75BvpJGqKzvyYduANusrxW3hjFv7OeGnBqQQjfKLJuYM4YCg"
  }
}