{
  "@context": [
    "https://www.w3.org/2018/credentials/v1",
    "https://w3id.org/security/suites/jws-2020/v1"
  ],
  "id": "urn:uuid:789",
  "type": [
    "VerifiablePresentation"
  ],
  "holder": "did:example:123",
  "verifiableCredential": [],
  "proof": {
    "type": "JsonWebSignature2020",
    "created": "2021-09-26T21:00:26Z",
    "verificationMethod": "did:example:123#key-3",
    "proofPurpose": "authentication",
    "challenge": "123",
    "jws": "eyJhbGciOiJFUzM4NCIsImI2NCI6ZmFsc2UsImNyaXQiOlsiYjY0Il19..ONW3Ajc_ZduLYmB_Nw6gbZacIWm-c0bU1dnvHNYrvTu-JAddUQV7o4WNpAKaoAsZd83XkbIwp_JdH6WmnxwcHWu7nPKKiCD7l3buuBXhrmT5sMI9v5e8-_jhjGj_BKmh"
  }
}