{
  "@context": [
    "https://www.w3.org/2018/credentials/v1",
    "https://w3id.org/security/suites/jws-2020/v1"
  ],
  "type": [
    "VerifiablePresentation"
  ],
  "holder": "did:example:123",
  "proof": {
    "type": "JsonWebSignature2020",
    "created": "2022-03-08T04:45:53Z",
    "verificationMethod": "did:example:123#key-2",
    "proofPurpose": "authentication",
    "challenge": "123",
    "jws": "eyJhbGciOiJFUzI1NiIsImI2NCI6ZmFsc2UsImNyaXQiOlsiYjY0Il19..2AEG0LYJURaA5-QlhqXF4g9U-aAvN7DeX_br2R4vG-9Z7J1JRCvHYjZOsqnbJnFc1P39gqPW_4t7dWXBf1zvwQ"
  }
}