{
  "@context": [
    "https://www.w3.org/2018/credentials/v1",
    "https://w3id.org/security/suites/jws-2020/v1"
  ],
  "type": [
    "VerifiableCredential"
  ],
  "credentialSubject": {},
  "issuer": "did:example:123",
  "issuanceDate": "2021-01-01T19:23:24Z",
  "proof": {
    "type": "JsonWebSignature2020",
    "proofPurpose": "assertionMethod",
    "verificationMethod": "did:example:123#key-2",
    "created": "2021-11-07T15:35:42.475Z",
    "jws": "eyJhbGciOiJFUzI1NiIsImNyaXQiOlsiYjY0Il0sImI2NCI6ZmFsc2V9..GLwneOAXvzmDWaFFAar4YWYGRdk0wOx7M3Gi1XfCPPexUFWSM9-vB73BGvTsbp7sox_xQtezzuW2nkBLWUDpTQ"
  }
}