{
  "@context": [
    "https://www.w3.org/2018/credentials/v1",
    "https://w3id.org/security/suites/jws-2020/v1",
    {
      "@vocab": "https://example.com/#"
    }
  ],
  "type": [
    "VerifiableCredential"
  ],
  "credentialSubject": {
    "id": "did:example:456",
    "type": "Person"
  },
  "issuer": "did:example:123",
  "issuanceDate": "2021-01-01T19:23:24Z",
  "proof": {
    "type": "JsonWebSignature2020",
    "proofPurpose": "assertionMethod",
    "verificationMethod": "did:example:123#key-1",
    "created": "2022-03-15T03:04:28.624Z",
    "jws": "eyJhbGciOiJFUzI1NksiLCJjcml0IjpbImI2NCJdLCJiNjQiOmZhbHNlfQ..NnzA5yezAdE891SV1cjZHhCMxY5RNEmtAz2ZN6wV-1oip9UhfM94ULe8JaTu0m8yQOqwc7dsj9TI13clHDdkIw"
  },
  "expirationDate": "2031-01-01T19:23:24Z"
}