{
  "@context": [
    "https://www.w3.org/2018/credentials/v1",
    "https://w3id.org/security/suites/jws-2020/v1",
    {
      "@vocab": "https://example.com/#"
    }
  ],
  "type": [
    "VerifiableCredential"
  ],
  "credentialSubject": {
    "id": "did:example:456",
    "type": "Person"
  },
  "issuer": "did:example:123",
  "issuanceDate": "2021-01-01T19:23:24Z",
  "proof": {
    "type": "JsonWebSignature2020",
    "proofPurpose": "assertionMethod",
    "verificationMethod": "did:example:123#key-2",
    "created": "2022-03-08T07:07:45.863Z",
    "jws": "eyJhbGciOiJFUzI1NiIsImNyaXQiOlsiYjY0Il0sImI2NCI6ZmFsc2V9..Pq6DGn90oEjJ0u8syzVYoP9O3vQRANj2PbyfYLXDI55aDv-LAFhWkvFCd0jWfaVALNErZEJQjHFLlboJUqwP6g"
  },
  "expirationDate": "2031-01-01T19:23:24Z"
}