{
  "@context": [
    "https://www.w3.org/2018/credentials/v1",
    "https://w3id.org/security/suites/jws-2020/v1",
    {
      "@vocab": "https://example.com/#"
    }
  ],
  "type": [
    "VerifiableCredential"
  ],
  "credentialSubject": {
    "id": "did:example:456",
    "type": "Person"
  },
  "issuer": "did:example:123",
  "issuanceDate": "2021-01-01T19:23:24Z",
  "proof": {
    "type": "JsonWebSignature2020",
    "proofPurpose": "assertionMethod",
    "verificationMethod": "did:example:123#key-2",
    "created": "2021-12-04T07:13:03.093Z",
    "jws": "eyJhbGciOiJFUzI1NiIsImNyaXQiOlsiYjY0Il0sImI2NCI6ZmFsc2V9..qnB3k0U4JQk9lF9RZQVr6h57GANFns5UXTdR3i-Ey5xOE6H0bWLe54p-qO9pqTCioF-S4TiXqNMCGG8edvWn0g"
  },
  "expirationDate": "2031-01-01T19:23:24Z"
}