{
  "@context": [
    "https://www.w3.org/2018/credentials/v1",
    "https://w3id.org/security/suites/jws-2020/v1"
  ],
  "type": [
    "VerifiableCredential"
  ],
  "credentialSubject": {},
  "issuer": "did:example:123",
  "issuanceDate": "2021-01-01T19:23:24Z",
  "proof": {
    "type": "JsonWebSignature2020",
    "proofPurpose": "assertionMethod",
    "verificationMethod": "did:example:123#key-0",
    "created": "2022-01-24T22:30:09.536Z",
    "jws": "eyJhbGciOiJFZERTQSIsImNyaXQiOlsiYjY0Il0sImI2NCI6ZmFsc2V9..mbw89k2sQbt9vigqLPPQDEaajq9W366ESLO8y3PQZOhCp0cga-A301JjqHk5Wg09gE1O70AI4kNo3WD1EclbAw"
  }
}