{
  "@context" : [ "https://www.w3.org/2018/credentials/v1", "https://w3id.org/security/suites/jws-2020/v1", {
    "@vocab" : "https://example.com/#"
  } ],
  "type" : [ "VerifiableCredential" ],
  "issuer" : "did:example:123",
  "issuanceDate" : "2022-03-19T15:20:55Z",
  "credentialSubject" : {
    "foo" : "bar"
  },
  "proof" : {
    "type" : "JsonWebSignature2020",
    "created" : "2022-05-27T19:04:05Z",
    "challenge" : "123",
    "proofPurpose" : "assertionMethod",
    "verificationMethod" : "did:example:123#key-1",
    "jws" : "eyJiNjQiOmZhbHNlLCJjcml0IjpbImI2NCJdLCJhbGciOiJFUzI1NksifQ.._spTVdmUy_Nnom3l1PRdNnvth9ra4gczi_t57hWc_3xnf3ijMiDrstP2wq3O5gIV_3uGs3R7rDDHjBlx166RCQ"
  }
}