{
  "@context" : [ "https://www.w3.org/2018/credentials/v1", "https://w3id.org/security/suites/jws-2020/v1" ],
  "type" : [ "VerifiablePresentation" ],
  "proof" : {
    "type" : "JsonWebSignature2020",
    "created" : "2022-03-08T07:03:52Z",
    "challenge" : "123",
    "proofPurpose" : "authentication",
    "verificationMethod" : "did:example:123#key-1",
    "jws" : "eyJiNjQiOmZhbHNlLCJjcml0IjpbImI2NCJdLCJhbGciOiJFUzI1NksifQ..BcFqfMs5ASwFy4hhMd076h_8bOvo7VkXtvFCTH6dwnQfAInlRY9Ws14HOVxlIWsTB5O0P2V0u8ymTfv3xnze7w"
  }
}